[
  {
    "referrer": "link.juejin.cn",
    "count": 49,
    "uniques": 21
  },
  {
    "referrer": "github.com",
    "count": 40,
    "uniques": 28
  },
  {
    "referrer": "Google",
    "count": 38,
    "uniques": 16
  },
  {
    "referrer": "yuque.com",
    "count": 14,
    "uniques": 2
  },
  {
    "referrer": "link.zhihu.com",
    "count": 2,
    "uniques": 2
  },
  {
    "referrer": "cn.bing.com",
    "count": 2,
    "uniques": 1
  },
  {
    "referrer": "Bing",
    "count": 2,
    "uniques": 1
  },
  {
    "referrer": "t5qflskzzu.feishu.cn",
    "count": 1,
    "uniques": 1
  },
  {
    "referrer": "zhihu.com",
    "count": 1,
    "uniques": 1
  },
  {
    "referrer": "muyunyun.cn",
    "count": 1,
    "uniques": 1
  }
]