[
  {
    "referrer": "link.juejin.cn",
    "count": 264,
    "uniques": 24
  },
  {
    "referrer": "Google",
    "count": 53,
    "uniques": 15
  },
  {
    "referrer": "github.com",
    "count": 51,
    "uniques": 32
  },
  {
    "referrer": "link.zhihu.com",
    "count": 20,
    "uniques": 10
  },
  {
    "referrer": "link.segmentfault.com",
    "count": 5,
    "uniques": 1
  },
  {
    "referrer": "muyunyun.cn",
    "count": 4,
    "uniques": 3
  },
  {
    "referrer": "juejin.cn",
    "count": 4,
    "uniques": 1
  },
  {
    "referrer": "yuque.com",
    "count": 3,
    "uniques": 2
  },
  {
    "referrer": "leetcode.cn",
    "count": 2,
    "uniques": 1
  },
  {
    "referrer": "react-shopping-cart-67954.firebaseapp.com",
    "count": 1,
    "uniques": 1
  }
]