[
  {
    "referrer": "github.com",
    "count": 153,
    "uniques": 80
  },
  {
    "referrer": "link.juejin.cn",
    "count": 101,
    "uniques": 29
  },
  {
    "referrer": "Google",
    "count": 28,
    "uniques": 22
  },
  {
    "referrer": "link.zhihu.com",
    "count": 10,
    "uniques": 9
  },
  {
    "referrer": "muyunyun.cn",
    "count": 8,
    "uniques": 4
  },
  {
    "referrer": "docs.dc.servyou-it.com",
    "count": 2,
    "uniques": 1
  },
  {
    "referrer": "imooc.com",
    "count": 2,
    "uniques": 1
  },
  {
    "referrer": "jianshu.com",
    "count": 1,
    "uniques": 1
  },
  {
    "referrer": "mail.aliyun.com",
    "count": 1,
    "uniques": 1
  }
]