[
  {
    "referrer": "link.juejin.cn",
    "count": 91,
    "uniques": 28
  },
  {
    "referrer": "github.com",
    "count": 53,
    "uniques": 33
  },
  {
    "referrer": "Google",
    "count": 25,
    "uniques": 16
  },
  {
    "referrer": "muyunyun.cn",
    "count": 13,
    "uniques": 3
  },
  {
    "referrer": "link.zhihu.com",
    "count": 4,
    "uniques": 4
  },
  {
    "referrer": "cnblogs.com",
    "count": 4,
    "uniques": 1
  },
  {
    "referrer": "cn.bing.com",
    "count": 2,
    "uniques": 2
  },
  {
    "referrer": "imooc.com",
    "count": 2,
    "uniques": 1
  },
  {
    "referrer": "link.segmentfault.com",
    "count": 1,
    "uniques": 1
  },
  {
    "referrer": "shimo.im",
    "count": 1,
    "uniques": 1
  }
]